myenv/__init__.py
myenv/envs/__init__.py
myenv/envs/ori_optimize.py
myenv/wrappers/__init__.py
OriOptimization-0.0.4.dist-info/METADATA
OriOptimization-0.0.4.dist-info/WHEEL
OriOptimization-0.0.4.dist-info/top_level.txt
OriOptimization-0.0.4.dist-info/RECORD
