Metadata-Version: 2.1
Name: OriOptimization
Version: 0.0.4
Requires-Dist: gym
